mg2dsn/__init__.py
mg2dsn/_impl.py
mg2dsn-0.5.dist-info/entry_points.txt
mg2dsn-0.5.dist-info/LICENSE
mg2dsn-0.5.dist-info/WHEEL
mg2dsn-0.5.dist-info/METADATA
mg2dsn-0.5.dist-info/RECORD
