Metadata-Version: 2.1
Name: mg2dsn
Version: 0.5
Summary: Generate rfc6522 delivery status notifications from the Mailgun API.
Home-page: https://github.com/glyph/mg2dsn
License: UNKNOWN
Author: Glyph
Author-email: glyph@twistedmatrix.com
Requires-Python: >=3
Classifier: License :: OSI Approved :: MIT License
Classifier: Programming Language :: Python :: 3
Requires-Dist: attrs
Requires-Dist: secretly
Requires-Dist: treq
Requires-Dist: twisted[tls]
Requires-Dist: python-dateutil
Requires-Dist: pytz
